traffic_light.v
module traffic_light (
    input clk,
    input rst,
    output reg [2:0] light_A,
    output reg [2:0] light_B
);

    parameter red = 3'b001,
        yellow = 3'b010,
        green = 3'b100;
    
    parameter S0 = 3'b000,
        S1 = 3'b001,
        S2 = 3'b010,
        S3 = 3'b011,
        S4 = 3'b100,
        S5 = 3'b101;

    reg[2:0] state,next_state;
    //counter variables 
    reg[3:0] sixcounter;
    reg[3:0] onecounter;
    //counter outputs
    reg C6,C1;
    //counter enables
    reg en1,en6;

    initial begin 
        C1 = 0; C6 = 0; en1 = 0; en6 = 1;
        onecounter = 3'b000; sixcounter = 3'b000;
    end

    //modulo 6 counter
    always @(posedge clk, posedge rst) begin
        if(en6) begin
            if(rst)
                sixcounter <= 3'b000;
            else begin
                if( sixcounter == 3'b101 ) begin
                    sixcounter <= 3'b000;
                    C6 <= 1'b1;
                end
                else sixcounter <= sixcounter + 1;
            end    
        end
        else begin
            sixcounter <= 3'b000;
            C6 <= 1'b0;
        end
    end

    //modulo 1 counter
    always @(posedge clk, posedge rst) begin
        if(en1) begin
            if(rst)
                onecounter <= 3'b000;
            else begin
                if( onecounter == 3'b000 ) begin
                    onecounter <= 3'b000;
                    C1 <= 1'b1;
                end
                else onecounter <= onecounter + 1;
            end 
        end
        else begin
            onecounter <= 3'b000;
            C1 <= 1'b0;
        end
    end

    //changes state by each positive edge of clock
    always @(posedge clk, posedge rst) begin
        if(rst)
            state <= S0;
        else 
            state <= next_state;
    end

    //assigns values for each state
    always @(state) begin
        light_A <= red;
        light_B <= green;
        case(state)
            S0: begin
                light_A <= red; 
                light_B <= green;
            end
            S1: begin
                light_A <= red; 
                light_B <= yellow;
            end
            S2: begin
                light_A <= red; 
                light_B <= red;
            end
            S3: begin
                light_A <= green; 
                light_B <= red;
            end
            S4: begin
                light_A <= yellow; 
                light_B <= red;
            end
            S5: begin
                light_A <= red; 
                light_B <= red;
            end
        endcase
    end    

    //main block
    always @(state,C1,C6) begin
        //set default state to S0
        next_state <= S0;
        en1 <= 1'b0;
        en6 <= 1'b1;
        case(state)
            S0: begin
                if(C6) begin
                    //modulo 6 counter off and modulo 1 counter on
                    en6 <= 1'b0;
                    en1 <= 1'b1;
                    next_state <= S1;
               end
                else next_state <= S0; //stay 6 seconds
            end
            S1: begin
                if(C1) begin
                    //modulo 6 counter off and modulo 1 counter on
                    en6 <= 1'b0;
                    en1 <= 1'b1;
                    next_state <= S2;
                end
                else next_state <= S1; //stay 1 second
            end
            S2: begin
                if(C1) begin
                    //modulo 6 counter on and modulo 1 counter off
                    en1 <= 1'b0;
                    en6 <= 1'b1;
                    next_state <= S3;
                end
                else next_state <= S2; //stay 1 second
            end
            S3: begin
                if(C6) begin
                    //modulo 6 counter off and modulo 1 counter on
                    en6 <= 1'b0;
                    en1 <= 1'b1;
                    next_state <= S4;
                end
                else next_state <= S3; //stay 6 seconds
            end
            S4: begin
                if(C1) begin
                    //modulo 6 counter off and modulo 1 counter on
                    en1 <= 1'b1;
                    en6 <= 1'b0;
                    next_state <= S5;
                end
                else next_state <= S4; //stay 1 second
            end
            S5: begin
                if(C1) begin
                    //modulo 6 counter on and modulo 1 counter off
                    en1 <= 1'b0;
                    en6 <= 1'b1;
                    next_state <= S0;
                end
                else next_state <= S5; //stay 1 second
            
            end
        endcase
    end

endmodule

traffic_light-testbench.v
`include "traffic_light.v"
`timescale 1s / 100ms
module traffic_light_tb();

    reg clock,reset;
    wire [2:0] A,B;
    traffic_light tb(clock, reset, A, B);

initial begin

    $dumpfile("traffic_light-testbench.vcd");
	$dumpvars(0,traffic_light_tb);

    clock = 1'b0;
    reset = 1'b0;
end

always#0.5 clock = ~clock;

initial begin 
    #2 reset = 1'b1;
    #2 reset = 1'b0;
    #60 $finish;
end

endmodule

traffic_light-testbench.vcd
$date
	Fri Jan 19 10:44:43 2024
$end
$version
	Icarus Verilog
$end
$timescale
	100ms
$end
$scope module traffic_light_tb $end
$var wire 3 ! B [2:0] $end
$var wire 3 " A [2:0] $end
$var reg 1 # clock $end
$var reg 1 $ reset $end
$scope module tb $end
$var wire 1 # clk $end
$var wire 1 $ rst $end
$var parameter 3 % S0 $end
$var parameter 3 & S1 $end
$var parameter 3 ' S2 $end
$var parameter 3 ( S3 $end
$var parameter 3 ) S4 $end
$var parameter 3 * S5 $end
$var parameter 3 + green $end
$var parameter 3 , red $end
$var parameter 3 - yellow $end
$var reg 1 . C1 $end
$var reg 1 / C6 $end
$var reg 1 0 en1 $end
$var reg 1 1 en6 $end
$var reg 3 2 light_A [2:0] $end
$var reg 3 3 light_B [2:0] $end
$var reg 3 4 next_state [2:0] $end
$var reg 4 5 onecounter [3:0] $end
$var reg 4 6 sixcounter [3:0] $end
$var reg 3 7 state [2:0] $end
$upscope $end
$upscope $end
$enddefinitions $end
$comment Show the parameter values. $end
$dumpall
b10 -
b1 ,
b100 +
b101 *
b100 )
b11 (
b10 '
b1 &
b0 %
$end
#0
$dumpvars
bx 7
b0 6
b0 5
b0 4
bx 3
bx 2
11
00
0/
0.
0$
0#
bx "
bx !
$end
#5
b100 !
b100 3
b1 "
b1 2
b1 6
b0 7
1#
#10
0#
#15
b10 6
1#
#20
b0 6
0#
1$
#25
1#
#30
0#
#35
1#
#40
0#
0$
#45
b1 6
1#
#50
0#
#55
b10 6
1#
#60
0#
#65
b11 6
1#
#70
0#
#75
b100 6
1#
#80
0#
#85
b101 6
1#
#90
0#
#95
b1 4
10
01
1/
b0 6
1#
#100
0#
#105
b10 !
b10 3
01
10
b10 4
b1 7
1.
0/
1#
#110
0#
#115
11
00
b11 4
b1 !
b1 3
b10 7
1#
#120
0#
#125
b100 "
b100 2
b1 !
b1 3
b11 4
b11 7
0.
b1 6
1#
#130
0#
#135
b10 6
1#
#140
0#
#145
b11 6
1#
#150
0#
#155
b100 6
1#
#160
0#
#165
b101 6
1#
#170
0#
#175
10
01
b100 4
1/
b0 6
1#
#180
0#
#185
b1 !
b1 3
b10 "
b10 2
01
10
b101 4
b100 7
1.
0/
1#
#190
0#
#195
11
00
b0 4
b1 !
b1 3
b1 "
b1 2
b101 7
1#
#200
0#
#205
b100 !
b100 3
b0 7
0.
b1 6
1#
#210
0#
#215
b10 6
1#
#220
0#
#225
b11 6
1#
#230
0#
#235
b100 6
1#
#240
0#
#245
b101 6
1#
#250
0#
#255
b1 4
10
01
1/
b0 6
1#
#260
0#
#265
b10 !
b10 3
01
10
b10 4
b1 7
1.
0/
1#
#270
0#
#275
11
00
b11 4
b1 !
b1 3
b10 7
1#
#280
0#
#285
b100 "
b100 2
b1 !
b1 3
b11 4
b11 7
0.
b1 6
1#
#290
0#
#295
b10 6
1#
#300
0#
#305
b11 6
1#
#310
0#
#315
b100 6
1#
#320
0#
#325
b101 6
1#
#330
0#
#335
10
01
b100 4
1/
b0 6
1#
#340
0#
#345
b1 !
b1 3
b10 "
b10 2
01
10
b101 4
b100 7
1.
0/
1#
#350
0#
#355
11
00
b0 4
b1 !
b1 3
b1 "
b1 2
b101 7
1#
#360
0#
#365
b100 !
b100 3
b0 7
0.
b1 6
1#
#370
0#
#375
b10 6
1#
#380
0#
#385
b11 6
1#
#390
0#
#395
b100 6
1#
#400
0#
#405
b101 6
1#
#410
0#
#415
b1 4
10
01
1/
b0 6
1#
#420
0#
#425
b10 !
b10 3
01
10
b10 4
b1 7
1.
0/
1#
#430
0#
#435
11
00
b11 4
b1 !
b1 3
b10 7
1#
#440
0#
#445
b100 "
b100 2
b1 !
b1 3
b11 4
b11 7
0.
b1 6
1#
#450
0#
#455
b10 6
1#
#460
0#
#465
b11 6
1#
#470
0#
#475
b100 6
1#
#480
0#
#485
b101 6
1#
#490
0#
#495
10
01
b100 4
1/
b0 6
1#
#500
0#
#505
b1 !
b1 3
b10 "
b10 2
01
10
b101 4
b100 7
1.
0/
1#
#510
0#
#515
11
00
b0 4
b1 !
b1 3
b1 "
b1 2
b101 7
1#
#520
0#
#525
b100 !
b100 3
b0 7
0.
b1 6
1#
#530
0#
#535
b10 6
1#
#540
0#
#545
b11 6
1#
#550
0#
#555
b100 6
1#
#560
0#
#565
b101 6
1#
#570
0#
#575
b1 4
10
01
1/
b0 6
1#
#580
0#
#585
b10 !
b10 3
01
10
b10 4
b1 7
1.
0/
1#
#590
0#
#595
11
00
b11 4
b1 !
b1 3
b10 7
1#
#600
0#
#605
b100 "
b100 2
b1 !
b1 3
b11 4
b11 7
0.
b1 6
1#
#610
0#
#615
b10 6
1#
#620
0#
#625
b11 6
1#
#630
0#
#635
b100 6
1#
